nusstalker
