Metadata-Version: 1.1
Name: nusstalker
Version: 0.9
Summary: Stalk people in NUS
Home-page: https://github.com/jsyeo/nus-stalker
Author: Jason Yeo
Author-email: jasonyeo88@gmail.com
License: UNKNOWN
Download-URL: https://github.com/jsyeo/nus-stalker/tarball/master
Keywords: ldap,nus
Platform: UNKNOWN
